inferedge_moss/__init__.py
inferedge_moss/__init__.pyi
inferedge_moss/py.typed
inferedge_moss/client/moss_client.py
inferedge_moss/services/__init__.py
inferedge_moss/services/embedding_service.py
inferedge_moss/services/index_service.py
inferedge_moss/services/moss_service.py
inferedge_moss/utils/cloud_api_client.py
inferedge_moss/utils/serializers.py
inferedge_moss-1.0.0b12.dist-info/licenses/LICENSE.txt
inferedge_moss-1.0.0b12.dist-info/METADATA
inferedge_moss-1.0.0b12.dist-info/WHEEL
inferedge_moss-1.0.0b12.dist-info/top_level.txt
inferedge_moss-1.0.0b12.dist-info/RECORD
