Metadata-Version: 2.4
Name: inferedge-moss
Version: 1.0.0b12
Summary: Python SDK for semantic search with on-device AI capabilities
Author-email: "InferEdge Inc." <contact@usemoss.dev>
Project-URL: Homepage, https://github.com/usemoss/moss-samples
Project-URL: Repository, https://github.com/usemoss/moss-samples
Project-URL: Documentation, https://docs.usemoss.dev/
Keywords: search,semantic,embeddings,vector,usemoss,moss
Classifier: Development Status :: 4 - Beta
Classifier: Intended Audience :: Developers
Classifier: Programming Language :: Python :: 3
Classifier: Programming Language :: Python :: 3.10
Classifier: Programming Language :: Python :: 3.11
Classifier: Programming Language :: Python :: 3.12
Classifier: Programming Language :: Python :: 3.13
Classifier: Programming Language :: Python :: 3.14
Classifier: Topic :: Software Development :: Libraries :: Python Modules
Classifier: Topic :: Scientific/Engineering :: Artificial Intelligence
Requires-Python: >=3.10
License-File: LICENSE.txt
Requires-Dist: transformers>=4.21.0
Requires-Dist: numpy>=1.26.4
Requires-Dist: typing-extensions>=4.0.0
Requires-Dist: httpx>=0.25.0
Requires-Dist: onnxruntime>=1.12.0; python_version < "3.14"
Requires-Dist: inferedge-moss-core==0.3.0
Provides-Extra: dev
Requires-Dist: pytest>=8.4.2; extra == "dev"
Requires-Dist: pytest-asyncio>=1.2.0; extra == "dev"
Requires-Dist: tox>=4.0.0; extra == "dev"
Requires-Dist: black>=25.9.0; extra == "dev"
Requires-Dist: isort>=7.0.0; extra == "dev"
Requires-Dist: flake8>=7.3.0; extra == "dev"
Requires-Dist: mypy>=1.18.2; extra == "dev"
Requires-Dist: python-dotenv>=1.0.0; extra == "dev"
Requires-Dist: pdoc>=15.0.4; extra == "dev"
Requires-Dist: pydoc-markdown>=4.8.2; extra == "dev"
Requires-Dist: griffe>=0.40.0; extra == "dev"
Requires-Dist: pyyaml>=6.0; extra == "dev"
Dynamic: license-file
